aiopools/__init__.py
aiopools/test.py
AIOPools-0.1.0.dist-info/LICENSE
AIOPools-0.1.0.dist-info/METADATA
AIOPools-0.1.0.dist-info/WHEEL
AIOPools-0.1.0.dist-info/top_level.txt
AIOPools-0.1.0.dist-info/RECORD
