Metadata-Version: 2.1
Name: AIOPools
Version: 0.1.0
Summary: AIOPools is a lightweight library for building Python AsyncIO coroutine pools. | AIOPools 是一个轻量级的用于构建 Python AsyncIO 协程池的库。
Author: Cyberbolt
Author-email: dtconlyone@gmail.com
License: UNKNOWN
Platform: UNKNOWN
Classifier: Programming Language :: Python :: 3
Classifier: License :: OSI Approved :: MIT License
Classifier: Operating System :: OS Independent
License-File: LICENSE
